webgram/__init__.py
webgram/model.py
webgram/ssoup.py
webgram/util.py
webgram-0.0.41.dist-info/LICENSE
webgram-0.0.41.dist-info/METADATA
webgram-0.0.41.dist-info/WHEEL
webgram-0.0.41.dist-info/top_level.txt
webgram-0.0.41.dist-info/RECORD
