Metadata-Version: 2.1
Name: webgram
Version: 0.0.41
Summary: Telegram Web Util
Home-page: https://github.com/gaoyunzhi/webgram
Author: Yunzhi Gao
Author-email: gaoyunzhi@gmail.com
License: UNKNOWN
Platform: UNKNOWN
Classifier: Programming Language :: Python :: 3
Classifier: License :: OSI Approved :: GNU General Public License v3 (GPLv3)
Classifier: Operating System :: OS Independent
Requires-Python: >=3.0
License-File: LICENSE
Requires-Dist: cached-url
Requires-Dist: bs4
